{
    "code": 200,
    "msg": "ok",
    "data":{
        "start": 0,  
        "count": 10,  
        "total": 30, 
        "list":[
        {
            "id": 20001,  
            "desc": "在哪里生活都是一样的，没什么生活在别处。地铁上满头小辫的黑姑娘在电话里跟男朋友吵架，报馆里都是开会熬夜菜色的脸，咖啡馆里两个花白胡子老头对坐着看一下午人来人往……人类只是个概念，一代一代人都是相似的生活，这辈子决定你悲欢的就是你身边的几个人。",  
            "book_id":  1001, 
            "rate_num": 8,  
            "like_num": 13, 
            "create_time": "2017-02-10 23:32",
            "nickname": "细说往事",  
            "avatar": "http://127.0.0.1:8000/images/avatar-01.jpg"  
        },
        {
            "id": 22747,  
            "desc": "作为一个学理工出生的人，已经记不清上次用文字来表达自己感受是什么时候了，大概要追溯到我的高中时代吧。那个时候我是极其讨厌文字的，认为文字是一种毫无逻辑的东西，更体会不了它所能带来的美感，以至于完成每周的语文作业——周记，我每写一个字都就像要是从一张干瘪...",  
            "book_id":  1001, 
            "rate_num": 6,  
            "like_num": 2, 
            "create_time": "2017-01-26 08:56",
            "nickname": "寂静Hill",  
            "avatar": "http://127.0.0.1:8000/images/avatar-02.jpg"
        },
        {
            "id": 22748,  
            "desc": "作为一个学理工出生的人，已经记不清上次用文字来表达自己感受是什么时候了，大概要追溯到我的高中时代吧。那个时候我是极其讨厌文字的，认为文字是一种毫无逻辑的东西，更体会不了它所能带来的美感，以至于完成每周的语文作业——周记，我每写一个字都就像要是从一张干瘪...",  
            "book_id":  1001, 
            "rate_num": 4,  
            "like_num": 2, 
            "create_time": "2017-01-26 08:56",
            "nickname": "李光毅",  
            "avatar": "http://127.0.0.1:8000/images/avatar-03.jpg" 
        },
        {
            "id": 22748,  
            "desc": "作为一个学理工出生的人，已经记不清上次用文字来表达自己感受是什么时候了，大概要追溯到我的高中时代吧。那个时候我是极其讨厌文字的，认为文字是一种毫无逻辑的东西，更体会不了它所能带来的美感，以至于完成每周的语文作业——周记，我每写一个字都就像要是从一张干瘪...",  
            "book_id":  1001, 
            "rate_num": 2,  
            "like_num": 2, 
            "create_time": "2017-01-26 08:56",
            "nickname": "张艺谋",  
            "avatar": "http://127.0.0.1:8000/images/avatar-04.jpg"
        }
        ]
    }
}